{"updated":"2026-07-14T05:14:41.548890+00:00","symbols":[{"id":"SPX","name":"S&P 500","kind":"index","group":"Indices","last":7515.3398,"prevClose":7575.3901,"leveraged":false,"currency":"USD"},{"id":"NDX","name":"NASDAQ 100","kind":"index","group":"Indices","last":29264.0996,"prevClose":29825.1094,"leveraged":false,"currency":"USD"},{"id":"DJI","name":"Dow Jones","kind":"index","group":"Indices","last":52498.6406,"prevClose":52637.0117,"leveraged":false,"currency":"USD"},{"id":"IWM","name":"Russell 2000 (IWM)","kind":"etf","group":"Indices","last":293.48,"prevClose":295.99,"leveraged":false,"currency":"USD"},{"id":"STOXX50","name":"Euro Stoxx 50","kind":"index","group":"Indices","last":6271.02,"prevClose":6269.9702,"leveraged":false,"currency":"USD"},{"id":"SXXP","name":"STOXX Europe 600","kind":"index","group":"Indices","last":641.01,"prevClose":641.1,"leveraged":false,"currency":"USD"},{"id":"VIX","name":"VIX Volatility","kind":"index","group":"Indices","last":17.16,"prevClose":15.03,"leveraged":false,"currency":"USD"},{"id":"DXY","name":"US Dollar Index","kind":"index","group":"Indices","last":101.188,"prevClose":101.28,"leveraged":false,"currency":"USD"},{"id":"EURUSD","name":"EUR / USD","kind":"fx","group":"FX","last":1.1396,"prevClose":1.1404,"leveraged":false,"currency":"USD"},{"id":"CHFEUR","name":"CHF / EUR","kind":"fx","group":"FX","last":1.0782,"prevClose":1.0832,"leveraged":false,"currency":"USD"},{"id":"BTC","name":"Bitcoin","kind":"crypto","group":"Crypto","last":62763.8086,"prevClose":63758.2188,"leveraged":false,"currency":"USD"},{"id":"WTI","name":"WTI Crude Oil","kind":"commodity","group":"Commodities","last":79.84,"prevClose":78.14,"leveraged":false,"currency":"USD"},{"id":"BRENT","name":"Brent Crude (UKOIL)","kind":"commodity","group":"Commodities","last":84.93,"prevClose":83.3,"leveraged":false,"currency":"USD"},{"id":"XAUUSD","name":"Gold Spot","kind":"commodity","group":"Commodities","last":4027.0,"prevClose":3997.0,"leveraged":false,"currency":"USD"},{"id":"4GLD","name":"Xetra Gold (4GLD)","kind":"etf","group":"Commodities","last":113.29,"prevClose":115.43,"leveraged":false,"currency":"EUR"},{"id":"ACN","name":"Accenture","kind":"equity","group":"Stocks","last":138.52,"prevClose":135.23,"leveraged":false,"currency":"USD"},{"id":"SU","name":"Schneider Electric","kind":"equity","group":"Stocks","last":269.65,"prevClose":270.0,"leveraged":false,"currency":"EUR"},{"id":"NVDA","name":"NVIDIA","kind":"equity","group":"Stocks","last":203.53,"prevClose":210.96,"leveraged":false,"currency":"USD"},{"id":"MSFT","name":"Microsoft","kind":"equity","group":"Stocks","last":390.99,"prevClose":385.1,"leveraged":false,"currency":"USD"},{"id":"AMZN","name":"Amazon","kind":"equity","group":"Stocks","last":247.31,"prevClose":245.34,"leveraged":false,"currency":"USD"},{"id":"GOOGL","name":"Alphabet","kind":"equity","group":"Stocks","last":352.51,"prevClose":357.18,"leveraged":false,"currency":"USD"},{"id":"META","name":"Meta Platforms","kind":"equity","group":"Stocks","last":656.73,"prevClose":669.21,"leveraged":false,"currency":"USD"},{"id":"TSLA","name":"Tesla","kind":"equity","group":"Stocks","last":394.76,"prevClose":407.76,"leveraged":false,"currency":"USD"},{"id":"AAPL","name":"Apple","kind":"equity","group":"Stocks","last":317.31,"prevClose":315.32,"leveraged":false,"currency":"USD"},{"id":"LQQ","name":"Amundi NASDAQ-100 2x","kind":"etf","group":"ETFs","last":9.803,"prevClose":9.956,"leveraged":true,"currency":"EUR"}],"errors":[]}