{"updated":"2026-07-17T05:27:18.392783+00:00","symbols":[{"id":"SPX","name":"S&P 500","kind":"index","group":"Indices","last":7533.77,"prevClose":7572.3999,"leveraged":false,"currency":"USD"},{"id":"NDX","name":"NASDAQ 100","kind":"index","group":"Indices","last":29025.7695,"prevClose":29502.5996,"leveraged":false,"currency":"USD"},{"id":"DJI","name":"Dow Jones","kind":"index","group":"Indices","last":52552.9688,"prevClose":52658.6406,"leveraged":false,"currency":"USD"},{"id":"IWM","name":"Russell 2000 (IWM)","kind":"etf","group":"Indices","last":295.59,"prevClose":295.77,"leveraged":false,"currency":"USD"},{"id":"STOXX50","name":"Euro Stoxx 50","kind":"index","group":"Indices","last":6283.6099,"prevClose":6265.5801,"leveraged":false,"currency":"USD"},{"id":"SXXP","name":"STOXX Europe 600","kind":"index","group":"Indices","last":643.73,"prevClose":642.71,"leveraged":false,"currency":"USD"},{"id":"VIX","name":"VIX Volatility","kind":"index","group":"Indices","last":16.73,"prevClose":15.67,"leveraged":false,"currency":"USD"},{"id":"DXY","name":"US Dollar Index","kind":"index","group":"Indices","last":100.788,"prevClose":100.73,"leveraged":false,"currency":"USD"},{"id":"EURUSD","name":"EUR / USD","kind":"fx","group":"FX","last":1.144,"prevClose":1.147,"leveraged":false,"currency":"USD"},{"id":"CHFEUR","name":"CHF / EUR","kind":"fx","group":"FX","last":1.0803,"prevClose":1.0833,"leveraged":false,"currency":"USD"},{"id":"BTC","name":"Bitcoin","kind":"crypto","group":"Crypto","last":63247.9883,"prevClose":64712.375,"leveraged":false,"currency":"USD"},{"id":"WTI","name":"WTI Crude Oil","kind":"commodity","group":"Commodities","last":79.06,"prevClose":78.95,"leveraged":false,"currency":"USD"},{"id":"BRENT","name":"Brent Crude (UKOIL)","kind":"commodity","group":"Commodities","last":84.95,"prevClose":84.23,"leveraged":false,"currency":"USD"},{"id":"XAUUSD","name":"Gold Spot","kind":"commodity","group":"Commodities","last":3983.2,"prevClose":3985.6001,"leveraged":false,"currency":"USD"},{"id":"4GLD","name":"Xetra Gold (4GLD)","kind":"etf","group":"Commodities","last":112.77,"prevClose":113.84,"leveraged":false,"currency":"EUR"},{"id":"ACN","name":"Accenture","kind":"equity","group":"Stocks","last":144.61,"prevClose":137.02,"leveraged":false,"currency":"USD"},{"id":"SU","name":"Schneider Electric","kind":"equity","group":"Stocks","last":270.15,"prevClose":273.1,"leveraged":false,"currency":"EUR"},{"id":"NVDA","name":"NVIDIA","kind":"equity","group":"Stocks","last":207.4,"prevClose":212.5,"leveraged":false,"currency":"USD"},{"id":"MSFT","name":"Microsoft","kind":"equity","group":"Stocks","last":401.1,"prevClose":395.63,"leveraged":false,"currency":"USD"},{"id":"AMZN","name":"Amazon","kind":"equity","group":"Stocks","last":249.89,"prevClose":254.96,"leveraged":false,"currency":"USD"},{"id":"GOOGL","name":"Alphabet","kind":"equity","group":"Stocks","last":354.46,"prevClose":370.92,"leveraged":false,"currency":"USD"},{"id":"META","name":"Meta Platforms","kind":"equity","group":"Stocks","last":664.54,"prevClose":681.31,"leveraged":false,"currency":"USD"},{"id":"TSLA","name":"Tesla","kind":"equity","group":"Stocks","last":391.06,"prevClose":394.46,"leveraged":false,"currency":"USD"},{"id":"AAPL","name":"Apple","kind":"equity","group":"Stocks","last":333.26,"prevClose":327.5,"leveraged":false,"currency":"USD"},{"id":"LQQ","name":"Amundi NASDAQ-100 2x","kind":"etf","group":"ETFs","last":9.584,"prevClose":9.719,"leveraged":true,"currency":"EUR"}],"errors":[]}